first_rec/__init__.py
first_rec-1.0.0.dist-info/licenses/LICENSE
first_rec-1.0.0.dist-info/METADATA
first_rec-1.0.0.dist-info/WHEEL
first_rec-1.0.0.dist-info/top_level.txt
first_rec-1.0.0.dist-info/RECORD
