Metadata-Version: 2.4
Name: first-rec
Version: 1.0.0
Summary: Find first file record
Author: Matteo Watson
Author-email: <m.watson12@gmail.com>
License: MIT License
Classifier: Framework :: Flask
Classifier: Development Status :: 6 - Mature
Classifier: Programming Language :: Python :: 3
License-File: LICENSE
Dynamic: author
Dynamic: author-email
Dynamic: classifier
Dynamic: description
Dynamic: description-content-type
Dynamic: license
Dynamic: license-file
Dynamic: summary
